{"cameraMode":{"drawMode":0,"name":"Shaded","section":"Shading Mode"},"sceneLighting":false,"audioPlay":false,"sceneViewState":{"showFog":true,"showMaterialUpdate":false,"showSkybox":false,"showFlares":true,"showImageEffects":true,"showParticleSystems":true},"in2DMode":false,"pivot":{"x":4.946918487548828,"y":2.0246987342834474,"z":-6.1652960777282719},"rotation":{"x":0.0005244772764854133,"y":0.9899657368659973,"z":-0.003861654782667756,"w":0.14145727455615998},"size":3.948552370071411,"orthographic":false}